README.md
setup.py
diskspace/__init__.py
diskspace/argpar.py
diskspace/diskspace.py
diskspace/pathRender.py
diskspace/utils.py
diskspace.egg-info/PKG-INFO
diskspace.egg-info/SOURCES.txt
diskspace.egg-info/dependency_links.txt
diskspace.egg-info/entry_points.txt
diskspace.egg-info/top_level.txt