Metadata-Version: 1.0
Name: diskspace
Version: 1.0.3
Summary: Making it possible to use Linux df & du command on Windows
Home-page: https://github.com/AlexFlipnote/DiskSpace
Author: AlexFlipnote
Author-email: UNKNOWN
License: GNU v3
Platform: UNKNOWN
